mozloc/__init__.py
mozloc/__main__.py
mozloc/airport.py
mozloc/base.py
mozloc/exe.py
mozloc/macos_corelocation.py
mozloc/modules.py
mozloc/netman.py
mozloc/netsh.py
mozloc/utils.py
mozloc/web.py
mozloc/csv2kml/__init__.py
mozloc/csv2kml/__main__.py
mozloc/tests/__init__.py
mozloc/tests/test_kml.py
mozloc/tests/test_mozloc.py
mozloc-1.8.0.dist-info/LICENSE.txt
mozloc-1.8.0.dist-info/METADATA
mozloc-1.8.0.dist-info/WHEEL
mozloc-1.8.0.dist-info/top_level.txt
mozloc-1.8.0.dist-info/RECORD
