Metadata-Version: 2.1
Name: mozloc
Version: 1.8.0
Summary: Using Mozilla Location services, log location vs. time using WiFi or convert to KML.
Keywords: wifi,geolocation
Classifier: Development Status :: 5 - Production/Stable
Classifier: Environment :: Console
Classifier: Intended Audience :: Information Technology
Classifier: Intended Audience :: System Administrators
Classifier: Operating System :: POSIX :: Linux
Classifier: Operating System :: MacOS
Classifier: Operating System :: Microsoft :: Windows
Classifier: Programming Language :: Python :: 3
Classifier: Topic :: System :: Networking
Classifier: Topic :: Utilities
Requires-Python: >=3.9
License-File: LICENSE.txt
Requires-Dist: requests
Requires-Dist: pandas
Provides-Extra: lint
Requires-Dist: flake8; extra == "lint"
Requires-Dist: flake8-bugbear; extra == "lint"
Requires-Dist: flake8-builtins; extra == "lint"
Requires-Dist: flake8-blind-except; extra == "lint"
Requires-Dist: mypy; extra == "lint"
Requires-Dist: types-requests; extra == "lint"
Provides-Extra: tests
Requires-Dist: pytest; extra == "tests"
